dstack/__init__.py
dstack/version.py
dstack/_internal/__init__.py
dstack/_internal/settings.py
dstack/_internal/cli/__init__.py
dstack/_internal/cli/main.py
dstack/_internal/cli/commands/__init__.py
dstack/_internal/cli/commands/apply.py
dstack/_internal/cli/commands/config.py
dstack/_internal/cli/commands/delete.py
dstack/_internal/cli/commands/gateway.py
dstack/_internal/cli/commands/init.py
dstack/_internal/cli/commands/logs.py
dstack/_internal/cli/commands/pool.py
dstack/_internal/cli/commands/ps.py
dstack/_internal/cli/commands/run.py
dstack/_internal/cli/commands/server.py
dstack/_internal/cli/commands/stop.py
dstack/_internal/cli/commands/volume.py
dstack/_internal/cli/services/__init__.py
dstack/_internal/cli/services/args.py
dstack/_internal/cli/services/profile.py
dstack/_internal/cli/services/configurators/__init__.py
dstack/_internal/cli/services/configurators/base.py
dstack/_internal/cli/services/configurators/gateway.py
dstack/_internal/cli/services/configurators/run.py
dstack/_internal/cli/services/configurators/volume.py
dstack/_internal/cli/utils/__init__.py
dstack/_internal/cli/utils/common.py
dstack/_internal/cli/utils/gateway.py
dstack/_internal/cli/utils/rich.py
dstack/_internal/cli/utils/run.py
dstack/_internal/cli/utils/updates.py
dstack/_internal/cli/utils/volume.py
dstack/_internal/core/__init__.py
dstack/_internal/core/errors.py
dstack/_internal/core/backends/__init__.py
dstack/_internal/core/backends/aws/__init__.py
dstack/_internal/core/backends/aws/auth.py
dstack/_internal/core/backends/aws/compute.py
dstack/_internal/core/backends/aws/config.py
dstack/_internal/core/backends/aws/resources.py
dstack/_internal/core/backends/azure/__init__.py
dstack/_internal/core/backends/azure/auth.py
dstack/_internal/core/backends/azure/compute.py
dstack/_internal/core/backends/azure/config.py
dstack/_internal/core/backends/azure/utils.py
dstack/_internal/core/backends/base/__init__.py
dstack/_internal/core/backends/base/compute.py
chip_wallet_dstack-1.5.dist-info/LICENSE.md
chip_wallet_dstack-1.5.dist-info/METADATA
chip_wallet_dstack-1.5.dist-info/WHEEL
chip_wallet_dstack-1.5.dist-info/entry_points.txt
chip_wallet_dstack-1.5.dist-info/top_level.txt
chip_wallet_dstack-1.5.dist-info/RECORD
