Metadata-Version: 2.1
Name: chip-wallet-dstack
Version: 1.5
Summary: dstack is an open-source orchestration engine for running AI workloads on any cloud or on-premises.
Home-page: https://dstack.ai
Author: Andrey Cheptsov
Author-email: andrey@dstack.ai
Project-URL: Source, https://github.com/dstackai/dstack
Classifier: Development Status :: 2 - Pre-Alpha
Classifier: Topic :: Scientific/Engineering :: Artificial Intelligence
Classifier: License :: OSI Approved :: Mozilla Public License 2.0 (MPL 2.0)
Classifier: Programming Language :: Python :: 3
Requires-Python: >=3.8
License-File: LICENSE.md
Requires-Dist: pyyaml
Requires-Dist: requests
Requires-Dist: typing-extensions >=4.0.0
Requires-Dist: cryptography
Requires-Dist: packaging
Requires-Dist: python-dateutil
Requires-Dist: gitpython
Requires-Dist: jsonschema
Requires-Dist: paramiko
Requires-Dist: git-url-parse
Requires-Dist: cursor
Requires-Dist: rich
Requires-Dist: rich-argparse
Requires-Dist: tqdm
Requires-Dist: simple-term-menu
Requires-Dist: fastapi
Requires-Dist: starlette >=0.26.0
Requires-Dist: uvicorn
Requires-Dist: pydantic <2.0.0,>=1.10.10
Requires-Dist: pydantic-duality >=1.2.0
Requires-Dist: sqlalchemy[asyncio] >=2.0.0
Requires-Dist: sqlalchemy-utils >=0.40.0
Requires-Dist: alembic >=1.10.2
Requires-Dist: apscheduler <4
Requires-Dist: aiosqlite
Requires-Dist: aiohttp
Requires-Dist: websocket-client
Requires-Dist: watchfiles
Requires-Dist: python-multipart
Requires-Dist: filelock
Requires-Dist: docker >=6.0.0
Requires-Dist: python-dxf >=11.0.0
Requires-Dist: cachetools
Requires-Dist: dnspython
Requires-Dist: grpcio >=1.50
Requires-Dist: gpuhunt >=0.0.9
Requires-Dist: sentry-sdk[fastapi]
Requires-Dist: httpx
Requires-Dist: aiorwlock
Requires-Dist: python-json-logger
Requires-Dist: alembic-postgresql-enum
Provides-Extra: all
Requires-Dist: boto3 ; extra == 'all'
Requires-Dist: botocore ; extra == 'all'
Requires-Dist: azure-identity >=1.12.0 ; extra == 'all'
Requires-Dist: azure-mgmt-subscription >=3.1.1 ; extra == 'all'
Requires-Dist: azure-mgmt-compute >=29.1.0 ; extra == 'all'
Requires-Dist: azure-mgmt-network ==23.0.0b2 ; extra == 'all'
Requires-Dist: azure-mgmt-resource >=22.0.0 ; extra == 'all'
Requires-Dist: azure-mgmt-authorization >=3.0.0 ; extra == 'all'
Requires-Dist: google-auth >=2.3.0 ; extra == 'all'
Requires-Dist: google-cloud-storage >=2.0.0 ; extra == 'all'
Requires-Dist: google-cloud-compute >=1.5.0 ; extra == 'all'
Requires-Dist: google-cloud-logging >=2.0.0 ; extra == 'all'
Requires-Dist: google-api-python-client >=2.80.0 ; extra == 'all'
Requires-Dist: google-cloud-billing >=1.11.0 ; extra == 'all'
Requires-Dist: datacrunch ; extra == 'all'
Requires-Dist: kubernetes ; extra == 'all'
Requires-Dist: oci ; extra == 'all'
Provides-Extra: aws
Requires-Dist: boto3 ; extra == 'aws'
Requires-Dist: botocore ; extra == 'aws'
Provides-Extra: azure
Requires-Dist: azure-identity >=1.12.0 ; extra == 'azure'
Requires-Dist: azure-mgmt-subscription >=3.1.1 ; extra == 'azure'
Requires-Dist: azure-mgmt-compute >=29.1.0 ; extra == 'azure'
Requires-Dist: azure-mgmt-network ==23.0.0b2 ; extra == 'azure'
Requires-Dist: azure-mgmt-resource >=22.0.0 ; extra == 'azure'
Requires-Dist: azure-mgmt-authorization >=3.0.0 ; extra == 'azure'
Provides-Extra: datacrunch
Requires-Dist: datacrunch ; extra == 'datacrunch'
Provides-Extra: gcp
Requires-Dist: google-auth >=2.3.0 ; extra == 'gcp'
Requires-Dist: google-cloud-storage >=2.0.0 ; extra == 'gcp'
Requires-Dist: google-cloud-compute >=1.5.0 ; extra == 'gcp'
Requires-Dist: google-cloud-logging >=2.0.0 ; extra == 'gcp'
Requires-Dist: google-api-python-client >=2.80.0 ; extra == 'gcp'
Requires-Dist: google-cloud-billing >=1.11.0 ; extra == 'gcp'
Provides-Extra: kubernetes
Requires-Dist: kubernetes ; extra == 'kubernetes'
Provides-Extra: lambda
Requires-Dist: boto3 ; extra == 'lambda'
Requires-Dist: botocore ; extra == 'lambda'
Provides-Extra: oci
Requires-Dist: oci ; extra == 'oci'
